[
  {
    "year": 2015,
    "months": [
      {
        "month":"Oktober",
        "data": [
          {
            "category":"R채kningar",
            "amount":7000,
            "date":"2015-10-01",
            "by":"Michael"
          },
          {
            "category":"Mat",
            "amount":500,
            "date":"2015-10-05",
            "by":"Emelie"
          }
        ]
      },
      {
        "month":"September",
        "data": [
          {
            "category":"R채kningar",
            "amount":2000,
            "date":"2015-09-01",
            "by":"Michael"
          }
        ]
      }
    ]
  },
  {
    "year": 2014,
    "months": [
      {
        "month":"Januari",
        "data": [
          {
            "category":"R채kningar",
            "amount":1000,
            "date":"2015-10-01",
            "by":"Michael"
          }
        ]
      },
      {
        "month":"November",
        "data": [
          {
            "category":"R채kningar",
            "amount":20000,
            "date":"2015-09-01",
            "by":"Michael"
          }
        ]
      }
    ]
  }
]
